[
{"check_in": "2022-06-08", "check_out": "2022-06-12", "is_superhost": true, "host_id": "14747423", "price": 1076.0, "url": "https://www.airbnb.com/rooms/18343337", "bathrooms": 2.0, "bedrooms": 2, "is_business_travel_ready": false, "is_fully_refundable": null, "is_new_listing": false, "lat": 52.50733, "lng": 13.41642, "localized_city": "Berlin", "localized_neighborhood": "Kreuzberg", "listing_name": "Trendy & Cosy in Berlin Mitte!", "person_capacity": 5, "picture_count": 16, "reviews_count": 77, "room_type_category": "entire_home", "star_rating": 5.0, "avg_rating": 4.88, "can_instant_book": true, "monthly_price_factor": 0.9, "currency": "CAD", "num_beds": 0, "host_reviews": 0, "accuracy": 0, "checkin": 0, "cleanliness": 0, "communication": 0, "value": 0, "location": 0, "guest_satisfication": 0, "response_rate": 0, "response_time": ""},
{"check_in": "2022-06-08", "check_out": "2022-06-12", "is_superhost": false, "host_id": "441154173", "price": 1416.0, "url": "https://www.airbnb.com/rooms/589682361143911982", "bathrooms": 1.0, "bedrooms": 1, "is_business_travel_ready": false, "is_fully_refundable": null, "is_new_listing": false, "lat": 52.54349389830764, "lng": 13.366970977923783, "localized_city": "Berlin", "localized_neighborhood": "Mitte", "listing_name": "limehome Berlin M\u00fcllerstr. - Suite L + sofa bed", "person_capacity": 3, "picture_count": 26, "reviews_count": 0, "room_type_category": "entire_home", "star_rating": null, "avg_rating": null, "can_instant_book": true, "monthly_price_factor": 0.75, "currency": "CAD", "num_beds": 0, "host_reviews": 0, "accuracy": 0, "checkin": 0, "cleanliness": 0, "communication": 0, "value": 0, "location": 0, "guest_satisfication": 0, "response_rate": 0, "response_time": ""},
{"check_in": "2022-06-08", "check_out": "2022-06-12", "is_superhost": false, "host_id": "215175725", "price": 1082.0, "url": "https://www.airbnb.com/rooms/28535860", "bathrooms": 1.0, "bedrooms": 1, "is_business_travel_ready": false, "is_fully_refundable": null, "is_new_listing": false, "lat": 52.50329, "lng": 13.37034, "localized_city": "Berlin", "localized_neighborhood": "Kreuzberg", "listing_name": "SCH\u00d8NES (fjord hotel berlin)", "person_capacity": 2, "picture_count": 9, "reviews_count": 267, "room_type_category": "hotel_room", "star_rating": 5.0, "avg_rating": 4.78, "can_instant_book": true, "monthly_price_factor": 0.0, "currency": "CAD", "num_beds": 0, "host_reviews": 0, "accuracy": 0, "checkin": 0, "cleanliness": 0, "communication": 0, "value": 0, "location": 0, "guest_satisfication": 0, "response_rate": 0, "response_time": ""},
{"check_in": "2022-06-08", "check_out": "2022-06-12", "is_superhost": false, "host_id": "185679076", "price": 535.0, "url": "https://www.airbnb.com/rooms/24573909", "bathrooms": 1.0, "bedrooms": 1, "is_business_travel_ready": false, "is_fully_refundable": null, "is_new_listing": false, "lat": 52.55283, "lng": 13.40656, "localized_city": "Berlin", "localized_neighborhood": "Prenzlauer Berg", "listing_name": "Peaceful and bright place in berlin`s heart.", "person_capacity": 2, "picture_count": 14, "reviews_count": 73, "room_type_category": "private_room", "star_rating": 4.5, "avg_rating": 4.7, "can_instant_book": false, "monthly_price_factor": 0.0, "currency": "CAD", "num_beds": 0, "host_reviews": 0, "accuracy": 0, "checkin": 0, "cleanliness": 0, "communication": 0, "value": 0, "location": 0, "guest_satisfication": 0, "response_rate": 0, "response_time": ""},
{"check_in": "2022-06-08", "check_out": "2022-06-12", "is_superhost": false, "host_id": "17997010", "price": 584.0, "url": "https://www.airbnb.com/rooms/17776272", "bathrooms": 1.0, "bedrooms": 1, "is_business_travel_ready": false, "is_fully_refundable": null, "is_new_listing": false, "lat": 52.50366, "lng": 13.3432, "localized_city": "Berlin", "localized_neighborhood": "Sch\u00f6neberg", "listing_name": "KaDeWe and ZOO! Business and Fun!", "person_capacity": 2, "picture_count": 14, "reviews_count": 45, "room_type_category": "private_room", "star_rating": 5.0, "avg_rating": 4.84, "can_instant_book": false, "monthly_price_factor": 0.9, "currency": "CAD", "num_beds": 0, "host_reviews": 0, "accuracy": 0, "checkin": 0, "cleanliness": 0, "communication": 0, "value": 0, "location": 0, "guest_satisfication": 0, "response_rate": 0, "response_time": ""},
{"check_in": "2022-06-08", "check_out": "2022-06-12", "is_superhost": false, "host_id": "435186074", "price": 778.0, "url": "https://www.airbnb.com/rooms/53746356", "bathrooms": 1.0, "bedrooms": 1, "is_business_travel_ready": false, "is_fully_refundable": null, "is_new_listing": false, "lat": 52.496513, "lng": 13.347855, "localized_city": "Berlin", "localized_neighborhood": "Sch\u00f6neberg", "listing_name": "Double room", "person_capacity": 2, "picture_count": 38, "reviews_count": 60, "room_type_category": "private_room", "star_rating": 4.5, "avg_rating": 4.53, "can_instant_book": true, "monthly_price_factor": 0.97, "currency": "CAD", "num_beds": 0, "host_reviews": 0, "accuracy": 0, "checkin": 0, "cleanliness": 0, "communication": 0, "value": 0, "location": 0, "guest_satisfication": 0, "response_rate": 0, "response_time": ""},
{"check_in": "2022-06-08", "check_out": "2022-06-12", "is_superhost": false, "host_id": "372068633", "price": 1248.0, "url": "https://www.airbnb.com/rooms/45944147", "bathrooms": 1.0, "bedrooms": 1, "is_business_travel_ready": false, "is_fully_refundable": null, "is_new_listing": false, "lat": 52.49523, "lng": 13.3317, "localized_city": "Berlin", "localized_neighborhood": "Charlottenburg-Wilmersdorf", "listing_name": "Junior Studio on Prague Square", "person_capacity": 3, "picture_count": 10, "reviews_count": 2, "room_type_category": "entire_home", "star_rating": null, "avg_rating": null, "can_instant_book": true, "monthly_price_factor": 0.0, "currency": "CAD", "num_beds": 0, "host_reviews": 0, "accuracy": 0, "checkin": 0, "cleanliness": 0, "communication": 0, "value": 0, "location": 0, "guest_satisfication": 0, "response_rate": 0, "response_time": ""},
{"check_in": "2022-06-08", "check_out": "2022-06-12", "is_superhost": false, "host_id": "390059085", "price": 1550.0, "url": "https://www.airbnb.com/rooms/49299676", "bathrooms": 1.0, "bedrooms": 1, "is_business_travel_ready": false, "is_fully_refundable": null, "is_new_listing": false, "lat": 52.52838, "lng": 13.41057, "localized_city": "Berlin", "localized_neighborhood": "Prenzlauer Berg", "listing_name": "SCHOENHOUSE by limehome - Junior Suite", "person_capacity": 2, "picture_count": 5, "reviews_count": 16, "room_type_category": "entire_home", "star_rating": 4.5, "avg_rating": 4.31, "can_instant_book": true, "monthly_price_factor": 0.75, "currency": "CAD", "num_beds": 0, "host_reviews": 0, "accuracy": 0, "checkin": 0, "cleanliness": 0, "communication": 0, "value": 0, "location": 0, "guest_satisfication": 0, "response_rate": 0, "response_time": ""},
{"check_in": "2022-06-08", "check_out": "2022-06-12", "is_superhost": false, "host_id": "21390864", "price": 757.0, "url": "https://www.airbnb.com/rooms/40944078", "bathrooms": 1.0, "bedrooms": 1, "is_business_travel_ready": false, "is_fully_refundable": null, "is_new_listing": false, "lat": 52.51478, "lng": 13.45527, "localized_city": "Berlin", "localized_neighborhood": "Friedrichshain", "listing_name": "Creative accommodation in the <3 of Friedrichshain", "person_capacity": 2, "picture_count": 19, "reviews_count": 0, "room_type_category": "private_room", "star_rating": null, "avg_rating": null, "can_instant_book": false, "monthly_price_factor": 0.0, "currency": "CAD", "num_beds": 0, "host_reviews": 0, "accuracy": 0, "checkin": 0, "cleanliness": 0, "communication": 0, "value": 0, "location": 0, "guest_satisfication": 0, "response_rate": 0, "response_time": ""},
{"check_in": "2022-06-08", "check_out": "2022-06-12", "is_superhost": false, "host_id": "182558424", "price": 994.0, "url": "https://www.airbnb.com/rooms/619217348977875183", "bathrooms": 1.0, "bedrooms": 2, "is_business_travel_ready": false, "is_fully_refundable": null, "is_new_listing": true, "lat": 52.54622012117098, "lng": 13.349087202002494, "localized_city": "Berlin", "localized_neighborhood": null, "listing_name": "Boutique Altbau Apartment Wedding", "person_capacity": 5, "picture_count": 0, "reviews_count": 0, "room_type_category": "entire_home", "star_rating": null, "avg_rating": null, "can_instant_book": true, "monthly_price_factor": 0.0, "currency": "CAD", "num_beds": 0, "host_reviews": 0, "accuracy": 0, "checkin": 0, "cleanliness": 0, "communication": 0, "value": 0, "location": 0, "guest_satisfication": 0, "response_rate": 0, "response_time": ""},
{"check_in": "2022-06-08", "check_out": "2022-06-12", "is_superhost": false, "host_id": "441154173", "price": 1231.0, "url": "https://www.airbnb.com/rooms/589639506430488668", "bathrooms": 1.0, "bedrooms": 1, "is_business_travel_ready": false, "is_fully_refundable": null, "is_new_listing": false, "lat": 52.54197, "lng": 13.36713, "localized_city": "Berlin", "localized_neighborhood": "Mitte", "listing_name": "limehome Berlin M\u00fcllerstr. - Suite M", "person_capacity": 2, "picture_count": 14, "reviews_count": 12, "room_type_category": "entire_home", "star_rating": 4.5, "avg_rating": 4.42, "can_instant_book": true, "monthly_price_factor": 0.75, "currency": "CAD", "num_beds": 0, "host_reviews": 0, "accuracy": 0, "checkin": 0, "cleanliness": 0, "communication": 0, "value": 0, "location": 0, "guest_satisfication": 0, "response_rate": 0, "response_time": ""},
{"check_in": "2022-06-08", "check_out": "2022-06-12", "is_superhost": false, "host_id": "371776088", "price": 1465.0, "url": "https://www.airbnb.com/rooms/46864858", "bathrooms": 1.0, "bedrooms": 1, "is_business_travel_ready": false, "is_fully_refundable": null, "is_new_listing": false, "lat": 52.51177, "lng": 13.4559, "localized_city": "Berlin", "localized_neighborhood": "Friedrichshain", "listing_name": "numa | Contemporary Studio near Boxhagener Platz", "person_capacity": 2, "picture_count": 4, "reviews_count": 498, "room_type_category": "entire_home", "star_rating": 4.5, "avg_rating": 4.68, "can_instant_book": true, "monthly_price_factor": 0.75, "currency": "CAD", "num_beds": 0, "host_reviews": 0, "accuracy": 0, "checkin": 0, "cleanliness": 0, "communication": 0, "value": 0, "location": 0, "guest_satisfication": 0, "response_rate": 0, "response_time": ""},
{"check_in": "2022-06-08", "check_out": "2022-06-12", "is_superhost": true, "host_id": "241486369", "price": 481.0, "url": "https://www.airbnb.com/rooms/44153090", "bathrooms": 1.0, "bedrooms": 1, "is_business_travel_ready": false, "is_fully_refundable": null, "is_new_listing": false, "lat": 52.55485, "lng": 13.37996, "localized_city": "Berlin", "localized_neighborhood": "Mitte", "listing_name": "Beautiful 2 rooms in Berlin studio apartment", "person_capacity": 2, "picture_count": 6, "reviews_count": 10, "room_type_category": "private_room", "star_rating": 5.0, "avg_rating": 5.0, "can_instant_book": false, "monthly_price_factor": 0.0, "currency": "CAD", "num_beds": 0, "host_reviews": 0, "accuracy": 0, "checkin": 0, "cleanliness": 0, "communication": 0, "value": 0, "location": 0, "guest_satisfication": 0, "response_rate": 0, "response_time": ""},
{"check_in": "2022-06-08", "check_out": "2022-06-12", "is_superhost": false, "host_id": "17997010", "price": 584.0, "url": "https://www.airbnb.com/rooms/11277910", "bathrooms": 1.0, "bedrooms": 1, "is_business_travel_ready": false, "is_fully_refundable": null, "is_new_listing": false, "lat": 52.50286, "lng": 13.34345, "localized_city": "Berlin", "localized_neighborhood": "Sch\u00f6neberg", "listing_name": "City Hospitality. Perfect place for perfekt money!", "person_capacity": 1, "picture_count": 5, "reviews_count": 50, "room_type_category": "private_room", "star_rating": 5.0, "avg_rating": 4.94, "can_instant_book": true, "monthly_price_factor": 0.9, "currency": "CAD", "num_beds": 0, "host_reviews": 0, "accuracy": 0, "checkin": 0, "cleanliness": 0, "communication": 0, "value": 0, "location": 0, "guest_satisfication": 0, "response_rate": 0, "response_time": ""},
{"check_in": "2022-06-08", "check_out": "2022-06-12", "is_superhost": true, "host_id": "210700814", "price": 1263.0, "url": "https://www.airbnb.com/rooms/42630872", "bathrooms": 1.0, "bedrooms": 0, "is_business_travel_ready": false, "is_fully_refundable": null, "is_new_listing": false, "lat": 52.53148, "lng": 13.38848, "localized_city": "Berlin", "localized_neighborhood": "Mitte", "listing_name": "Urban Life Studio, 40 qm", "person_capacity": 3, "picture_count": 16, "reviews_count": 3, "room_type_category": "entire_home", "star_rating": 5.0, "avg_rating": 5.0, "can_instant_book": true, "monthly_price_factor": 0.0, "currency": "CAD", "num_beds": 0, "host_reviews": 0, "accuracy": 0, "checkin": 0, "cleanliness": 0, "communication": 0, "value": 0, "location": 0, "guest_satisfication": 0, "response_rate": 0, "response_time": ""},
{"check_in": "2022-06-08", "check_out": "2022-06-12", "is_superhost": true, "host_id": "87442687", "price": 1823.0, "url": "https://www.airbnb.com/rooms/42059405", "bathrooms": 2.0, "bedrooms": 5, "is_business_travel_ready": false, "is_fully_refundable": null, "is_new_listing": false, "lat": 52.53404, "lng": 13.35112, "localized_city": "Berlin", "localized_neighborhood": "Mitte", "listing_name": "Fritz Castle Apartment", "person_capacity": 10, "picture_count": 61, "reviews_count": 1, "room_type_category": "entire_home", "star_rating": null, "avg_rating": null, "can_instant_book": false, "monthly_price_factor": 0.0, "currency": "CAD", "num_beds": 0, "host_reviews": 0, "accuracy": 0, "checkin": 0, "cleanliness": 0, "communication": 0, "value": 0, "location": 0, "guest_satisfication": 0, "response_rate": 0, "response_time": ""},
{"check_in": "2022-06-08", "check_out": "2022-06-12", "is_superhost": false, "host_id": "364655610", "price": 553.0, "url": "https://www.airbnb.com/rooms/45170497", "bathrooms": 1.0, "bedrooms": 0, "is_business_travel_ready": false, "is_fully_refundable": null, "is_new_listing": false, "lat": 52.53421, "lng": 13.39701, "localized_city": "Berlin", "localized_neighborhood": "Mitte", "listing_name": "Cozy Quiet Apartment in the center of Berlin", "person_capacity": 2, "picture_count": 5, "reviews_count": 77, "room_type_category": "entire_home", "star_rating": 4.5, "avg_rating": 4.69, "can_instant_book": true, "monthly_price_factor": 0.8, "currency": "CAD", "num_beds": 0, "host_reviews": 0, "accuracy": 0, "checkin": 0, "cleanliness": 0, "communication": 0, "value": 0, "location": 0, "guest_satisfication": 0, "response_rate": 0, "response_time": ""},
{"check_in": "2022-06-08", "check_out": "2022-06-12", "is_superhost": true, "host_id": "327601894", "price": 1305.0, "url": "https://www.airbnb.com/rooms/41572122", "bathrooms": 1.0, "bedrooms": 1, "is_business_travel_ready": false, "is_fully_refundable": null, "is_new_listing": false, "lat": 52.50921, "lng": 13.31444, "localized_city": "Berlin ", "localized_neighborhood": "Charlottenburg", "listing_name": "Beautiful sunny loft with big rooftop terrace", "person_capacity": 2, "picture_count": 20, "reviews_count": 59, "room_type_category": "entire_home", "star_rating": 5.0, "avg_rating": 4.98, "can_instant_book": true, "monthly_price_factor": 0.9, "currency": "CAD", "num_beds": 0, "host_reviews": 0, "accuracy": 0, "checkin": 0, "cleanliness": 0, "communication": 0, "value": 0, "location": 0, "guest_satisfication": 0, "response_rate": 0, "response_time": ""},
{"check_in": "2022-06-08", "check_out": "2022-06-12", "is_superhost": false, "host_id": "364655610", "price": 553.0, "url": "https://www.airbnb.com/rooms/45170497", "bathrooms": 1.0, "bedrooms": 0, "is_business_travel_ready": false, "is_fully_refundable": null, "is_new_listing": false, "lat": 52.53421, "lng": 13.39701, "localized_city": "Berlin", "localized_neighborhood": "Mitte", "listing_name": "Cozy Quiet Apartment in the center of Berlin", "person_capacity": 2, "picture_count": 5, "reviews_count": 77, "room_type_category": "entire_home", "star_rating": 4.5, "avg_rating": 4.69, "can_instant_book": true, "monthly_price_factor": 0.8, "currency": "CAD", "num_beds": 0, "host_reviews": 0, "accuracy": 0, "checkin": 0, "cleanliness": 0, "communication": 0, "value": 0, "location": 0, "guest_satisfication": 0, "response_rate": 0, "response_time": ""},
{"check_in": "2022-06-08", "check_out": "2022-06-12", "is_superhost": false, "host_id": "177712632", "price": 751.0, "url": "https://www.airbnb.com/rooms/50861603", "bathrooms": 1.0, "bedrooms": 0, "is_business_travel_ready": false, "is_fully_refundable": null, "is_new_listing": false, "lat": 52.52338, "lng": 13.44929, "localized_city": "Berlin", "localized_neighborhood": "Friedrichshain", "listing_name": "Friedrichshain - Petersburger Stra\u00dfe Studio Apartment", "person_capacity": 4, "picture_count": 10, "reviews_count": 0, "room_type_category": "entire_home", "star_rating": null, "avg_rating": null, "can_instant_book": false, "monthly_price_factor": 0.8, "currency": "CAD", "num_beds": 0, "host_reviews": 0, "accuracy": 0, "checkin": 0, "cleanliness": 0, "communication": 0, "value": 0, "location": 0, "guest_satisfication": 0, "response_rate": 0, "response_time": ""},
{"check_in": "2022-06-08", "check_out": "2022-06-12", "is_superhost": false, "host_id": "206926760", "price": 865.0, "url": "https://www.airbnb.com/rooms/45537719", "bathrooms": 1.5, "bedrooms": 1, "is_business_travel_ready": false, "is_fully_refundable": null, "is_new_listing": false, "lat": 52.5132, "lng": 13.46864, "localized_city": "Berlin", "localized_neighborhood": "Friedrichshain", "listing_name": "Super central flat in Friedrichshain", "person_capacity": 1, "picture_count": 32, "reviews_count": 2, "room_type_category": "entire_home", "star_rating": null, "avg_rating": null, "can_instant_book": false, "monthly_price_factor": 0.0, "currency": "CAD", "num_beds": 0, "host_reviews": 0, "accuracy": 0, "checkin": 0, "cleanliness": 0, "communication": 0, "value": 0, "location": 0, "guest_satisfication": 0, "response_rate": 0, "response_time": ""},
{"check_in": "2022-06-08", "check_out": "2022-06-12", "is_superhost": false, "host_id": "370237375", "price": 1070.0, "url": "https://www.airbnb.com/rooms/45693213", "bathrooms": null, "bedrooms": null, "is_business_travel_ready": false, "is_fully_refundable": null, "is_new_listing": false, "lat": 52.49691, "lng": 13.32385, "localized_city": "Berlin", "localized_neighborhood": null, "listing_name": "Max Brown Hotel Ku'Damm", "person_capacity": 0, "picture_count": 7, "reviews_count": 4, "room_type_category": "hotel_room", "star_rating": 5.0, "avg_rating": 4.75, "can_instant_book": true, "monthly_price_factor": 0.0, "currency": "CAD", "num_beds": 0, "host_reviews": 0, "accuracy": 0, "checkin": 0, "cleanliness": 0, "communication": 0, "value": 0, "location": 0, "guest_satisfication": 0, "response_rate": 0, "response_time": ""},
{"check_in": "2022-06-08", "check_out": "2022-06-12", "is_superhost": false, "host_id": "187655517", "price": 981.0, "url": "https://www.airbnb.com/rooms/25803218", "bathrooms": 1.0, "bedrooms": 1, "is_business_travel_ready": false, "is_fully_refundable": null, "is_new_listing": false, "lat": 52.49146, "lng": 13.3311, "localized_city": "Berlin", "localized_neighborhood": "Charlottenburg-Wilmersdorf", "listing_name": "Axel Superior Room at TWO Hotel Berlin by Axel", "person_capacity": 2, "picture_count": 23, "reviews_count": 1, "room_type_category": "hotel_room", "star_rating": null, "avg_rating": null, "can_instant_book": true, "monthly_price_factor": 0.0, "currency": "CAD", "num_beds": 0, "host_reviews": 0, "accuracy": 0, "checkin": 0, "cleanliness": 0, "communication": 0, "value": 0, "location": 0, "guest_satisfication": 0, "response_rate": 0, "response_time": ""},
{"check_in": "2022-06-08", "check_out": "2022-06-12", "is_superhost": true, "host_id": "373476835", "price": 778.0, "url": "https://www.airbnb.com/rooms/46084713", "bathrooms": 1.0, "bedrooms": 0, "is_business_travel_ready": false, "is_fully_refundable": null, "is_new_listing": false, "lat": 52.4983, "lng": 13.33839, "localized_city": "Berlin", "localized_neighborhood": "Sch\u00f6neberg", "listing_name": "Sch\u00f6neberg economy room", "person_capacity": 2, "picture_count": 16, "reviews_count": 3, "room_type_category": "private_room", "star_rating": 5.0, "avg_rating": 5.0, "can_instant_book": true, "monthly_price_factor": 0.0, "currency": "CAD", "num_beds": 0, "host_reviews": 0, "accuracy": 0, "checkin": 0, "cleanliness": 0, "communication": 0, "value": 0, "location": 0, "guest_satisfication": 0, "response_rate": 0, "response_time": ""},
{"check_in": "2022-06-08", "check_out": "2022-06-12", "is_superhost": false, "host_id": "213877372", "price": 915.0, "url": "https://www.airbnb.com/rooms/28537085", "bathrooms": 1.0, "bedrooms": 1, "is_business_travel_ready": false, "is_fully_refundable": null, "is_new_listing": false, "lat": 52.46545, "lng": 13.32632, "localized_city": "Berlin", "localized_neighborhood": "Steglitz", "listing_name": "Kleines (Anna 1908)", "person_capacity": 2, "picture_count": 8, "reviews_count": 24, "room_type_category": "hotel_room", "star_rating": 4.5, "avg_rating": 4.71, "can_instant_book": true, "monthly_price_factor": 0.0, "currency": "CAD", "num_beds": 0, "host_reviews": 0, "accuracy": 0, "checkin": 0, "cleanliness": 0, "communication": 0, "value": 0, "location": 0, "guest_satisfication": 0, "response_rate": 0, "response_time": ""},
{"check_in": "2022-06-08", "check_out": "2022-06-12", "is_superhost": false, "host_id": "185679076", "price": 535.0, "url": "https://www.airbnb.com/rooms/24573909", "bathrooms": 1.0, "bedrooms": 1, "is_business_travel_ready": false, "is_fully_refundable": null, "is_new_listing": false, "lat": 52.55283, "lng": 13.40656, "localized_city": "Berlin", "localized_neighborhood": "Prenzlauer Berg", "listing_name": "Peaceful and bright place in berlin`s heart.", "person_capacity": 2, "picture_count": 14, "reviews_count": 73, "room_type_category": "private_room", "star_rating": 4.5, "avg_rating": 4.7, "can_instant_book": false, "monthly_price_factor": 0.0, "currency": "CAD", "num_beds": 0, "host_reviews": 0, "accuracy": 0, "checkin": 0, "cleanliness": 0, "communication": 0, "value": 0, "location": 0, "guest_satisfication": 0, "response_rate": 0, "response_time": ""},
{"check_in": "2022-06-08", "check_out": "2022-06-12", "is_superhost": false, "host_id": "240204649", "price": 876.0, "url": "https://www.airbnb.com/rooms/36259013", "bathrooms": 1.0, "bedrooms": 1, "is_business_travel_ready": false, "is_fully_refundable": null, "is_new_listing": false, "lat": 52.52669, "lng": 13.41062, "localized_city": "Berlin", "localized_neighborhood": "Mitte", "listing_name": "Double Room Apartment with Shared Kitchen/Bathroom", "person_capacity": 2, "picture_count": 38, "reviews_count": 97, "room_type_category": "private_room", "star_rating": 4.5, "avg_rating": 4.31, "can_instant_book": true, "monthly_price_factor": 0.0, "currency": "CAD", "num_beds": 0, "host_reviews": 0, "accuracy": 0, "checkin": 0, "cleanliness": 0, "communication": 0, "value": 0, "location": 0, "guest_satisfication": 0, "response_rate": 0, "response_time": ""},
{"check_in": "2022-06-08", "check_out": "2022-06-12", "is_superhost": false, "host_id": "17997010", "price": 584.0, "url": "https://www.airbnb.com/rooms/17776272", "bathrooms": 1.0, "bedrooms": 1, "is_business_travel_ready": false, "is_fully_refundable": null, "is_new_listing": false, "lat": 52.50366, "lng": 13.3432, "localized_city": "Berlin", "localized_neighborhood": "Sch\u00f6neberg", "listing_name": "KaDeWe and ZOO! Business and Fun!", "person_capacity": 2, "picture_count": 14, "reviews_count": 45, "room_type_category": "private_room", "star_rating": 5.0, "avg_rating": 4.84, "can_instant_book": false, "monthly_price_factor": 0.9, "currency": "CAD", "num_beds": 0, "host_reviews": 0, "accuracy": 0, "checkin": 0, "cleanliness": 0, "communication": 0, "value": 0, "location": 0, "guest_satisfication": 0, "response_rate": 0, "response_time": ""},
{"check_in": "2022-06-08", "check_out": "2022-06-12", "is_superhost": false, "host_id": "255958728", "price": 570.0, "url": "https://www.airbnb.com/rooms/33894658", "bathrooms": 1.0, "bedrooms": 0, "is_business_travel_ready": false, "is_fully_refundable": null, "is_new_listing": false, "lat": 52.52444, "lng": 13.33053, "localized_city": "Berlin", "localized_neighborhood": "Mitte", "listing_name": "Moabit:) Sch\u00f6n Kulturell", "person_capacity": 2, "picture_count": 23, "reviews_count": 23, "room_type_category": "entire_home", "star_rating": 5.0, "avg_rating": 4.96, "can_instant_book": false, "monthly_price_factor": 0.0, "currency": "CAD", "num_beds": 0, "host_reviews": 0, "accuracy": 0, "checkin": 0, "cleanliness": 0, "communication": 0, "value": 0, "location": 0, "guest_satisfication": 0, "response_rate": 0, "response_time": ""},
{"check_in": "2022-06-08", "check_out": "2022-06-12", "is_superhost": false, "host_id": "215178674", "price": 901.0, "url": "https://www.airbnb.com/rooms/28532851", "bathrooms": 1.0, "bedrooms": 1, "is_business_travel_ready": false, "is_fully_refundable": null, "is_new_listing": false, "lat": 52.49379, "lng": 13.36134, "localized_city": "Berlin", "localized_neighborhood": "Sch\u00f6neberg", "listing_name": "Quiet & Small (LINDEMANN 'S)", "person_capacity": 2, "picture_count": 7, "reviews_count": 308, "room_type_category": "hotel_room", "star_rating": 4.5, "avg_rating": 4.7, "can_instant_book": true, "monthly_price_factor": 0.0, "currency": "CAD", "num_beds": 0, "host_reviews": 0, "accuracy": 0, "checkin": 0, "cleanliness": 0, "communication": 0, "value": 0, "location": 0, "guest_satisfication": 0, "response_rate": 0, "response_time": ""},
{"check_in": "2022-06-08", "check_out": "2022-06-12", "is_superhost": false, "host_id": "215175725", "price": 1082.0, "url": "https://www.airbnb.com/rooms/28535860", "bathrooms": 1.0, "bedrooms": 1, "is_business_travel_ready": false, "is_fully_refundable": null, "is_new_listing": false, "lat": 52.50329, "lng": 13.37034, "localized_city": "Berlin", "localized_neighborhood": "Kreuzberg", "listing_name": "SCH\u00d8NES (fjord hotel berlin)", "person_capacity": 2, "picture_count": 9, "reviews_count": 267, "room_type_category": "hotel_room", "star_rating": 5.0, "avg_rating": 4.78, "can_instant_book": true, "monthly_price_factor": 0.0, "currency": "CAD", "num_beds": 0, "host_reviews": 0, "accuracy": 0, "checkin": 0, "cleanliness": 0, "communication": 0, "value": 0, "location": 0, "guest_satisfication": 0, "response_rate": 0, "response_time": ""},
{"check_in": "2022-06-08", "check_out": "2022-06-12", "is_superhost": false, "host_id": "435186074", "price": 832.0, "url": "https://www.airbnb.com/rooms/53746356", "bathrooms": 1.0, "bedrooms": 1, "is_business_travel_ready": false, "is_fully_refundable": null, "is_new_listing": false, "lat": 52.496513, "lng": 13.347855, "localized_city": "Berlin", "localized_neighborhood": "Sch\u00f6neberg", "listing_name": "Double room", "person_capacity": 2, "picture_count": 38, "reviews_count": 60, "room_type_category": "private_room", "star_rating": 4.5, "avg_rating": 4.53, "can_instant_book": true, "monthly_price_factor": 0.97, "currency": "CAD", "num_beds": 0, "host_reviews": 0, "accuracy": 0, "checkin": 0, "cleanliness": 0, "communication": 0, "value": 0, "location": 0, "guest_satisfication": 0, "response_rate": 0, "response_time": ""},
{"check_in": "2022-06-08", "check_out": "2022-06-12", "is_superhost": false, "host_id": "21390864", "price": 757.0, "url": "https://www.airbnb.com/rooms/40944078", "bathrooms": 1.0, "bedrooms": 1, "is_business_travel_ready": false, "is_fully_refundable": null, "is_new_listing": false, "lat": 52.51478, "lng": 13.45527, "localized_city": "Berlin", "localized_neighborhood": "Friedrichshain", "listing_name": "Creative accommodation in the <3 of Friedrichshain", "person_capacity": 2, "picture_count": 19, "reviews_count": 0, "room_type_category": "private_room", "star_rating": null, "avg_rating": null, "can_instant_book": false, "monthly_price_factor": 0.0, "currency": "CAD", "num_beds": 0, "host_reviews": 0, "accuracy": 0, "checkin": 0, "cleanliness": 0, "communication": 0, "value": 0, "location": 0, "guest_satisfication": 0, "response_rate": 0, "response_time": ""},
{"check_in": "2022-06-08", "check_out": "2022-06-12", "is_superhost": true, "host_id": "241486369", "price": 481.0, "url": "https://www.airbnb.com/rooms/44153090", "bathrooms": 1.0, "bedrooms": 1, "is_business_travel_ready": false, "is_fully_refundable": null, "is_new_listing": false, "lat": 52.55485, "lng": 13.37996, "localized_city": "Berlin", "localized_neighborhood": "Mitte", "listing_name": "Beautiful 2 rooms in Berlin studio apartment", "person_capacity": 2, "picture_count": 6, "reviews_count": 10, "room_type_category": "private_room", "star_rating": 5.0, "avg_rating": 5.0, "can_instant_book": false, "monthly_price_factor": 0.0, "currency": "CAD", "num_beds": 0, "host_reviews": 0, "accuracy": 0, "checkin": 0, "cleanliness": 0, "communication": 0, "value": 0, "location": 0, "guest_satisfication": 0, "response_rate": 0, "response_time": ""},
{"check_in": "2022-06-08", "check_out": "2022-06-12", "is_superhost": false, "host_id": "381323865", "price": 988.0, "url": "https://www.airbnb.com/rooms/47215807", "bathrooms": 1.0, "bedrooms": 1, "is_business_travel_ready": false, "is_fully_refundable": null, "is_new_listing": false, "lat": 52.50893, "lng": 13.38818, "localized_city": "Berlin", "localized_neighborhood": "Kreuzberg", "listing_name": "Double Hotel Gat Point Charlie Berlin", "person_capacity": 2, "picture_count": 15, "reviews_count": 235, "room_type_category": "private_room", "star_rating": 4.5, "avg_rating": 4.53, "can_instant_book": true, "monthly_price_factor": 0.85, "currency": "CAD", "num_beds": 0, "host_reviews": 0, "accuracy": 0, "checkin": 0, "cleanliness": 0, "communication": 0, "value": 0, "location": 0, "guest_satisfication": 0, "response_rate": 0, "response_time": ""},
{"check_in": "2022-06-08", "check_out": "2022-06-12", "is_superhost": false, "host_id": "17997010", "price": 584.0, "url": "https://www.airbnb.com/rooms/11277910", "bathrooms": 1.0, "bedrooms": 1, "is_business_travel_ready": false, "is_fully_refundable": null, "is_new_listing": false, "lat": 52.50286, "lng": 13.34345, "localized_city": "Berlin", "localized_neighborhood": "Sch\u00f6neberg", "listing_name": "City Hospitality. Perfect place for perfekt money!", "person_capacity": 1, "picture_count": 5, "reviews_count": 50, "room_type_category": "private_room", "star_rating": 5.0, "avg_rating": 4.94, "can_instant_book": true, "monthly_price_factor": 0.9, "currency": "CAD", "num_beds": 0, "host_reviews": 0, "accuracy": 0, "checkin": 0, "cleanliness": 0, "communication": 0, "value": 0, "location": 0, "guest_satisfication": 0, "response_rate": 0, "response_time": ""}
]